<annotation>
	<folder></folder>
	<filename>Capture-d-ecran--682-_jpg.rf.1fa95bf42b1185732d4a6677e4e2e845.jpg</filename>
	<path>Capture-d-ecran--682-_jpg.rf.1fa95bf42b1185732d4a6677e4e2e845.jpg</path>
	<source>
		<database>roboflow.ai</database>
	</source>
	<size>
		<width>416</width>
		<height>416</height>
		<depth>3</depth>
	</size>
	<segmented>0</segmented>
	<object>
		<name>fail</name>
		<pose>Unspecified</pose>
		<truncated>0</truncated>
		<difficult>0</difficult>
		<occluded>0</occluded>
		<bndbox>
			<xmin>112</xmin>
			<xmax>375</xmax>
			<ymin>1</ymin>
			<ymax>364</ymax>
		</bndbox>
	</object>
</annotation>
